{
  "name": "Sapegin_Artem_20D_2007-02-12_272-7262",
  "slug": "20-2007-02-12-272-7262",
  "color": "#6878a8",
  "width": 1463,
  "height": 2048,
  "modified": "2026-02-17T12:23:42.000Z",
  "timestamp": "2007-02-12T06:56:36.000Z",
  "formattedDate": "February 2007",
  "title": "",
  "caption": "",
  "location": "",
  "keywords": [
    "Moscow",
    "Russia",
    "bird",
    "butovo-1-0",
    "church",
    "city",
    "cityscape",
    "dawn",
    "out-my-window",
    "sunrise",
    "when-the-moon-goes-to-bed"
  ],
  "rating": 5
}