{
  "createdAt": "2021-07-13T15:56:20.227Z",
  "cuisines": [
    "UnitedStates"
  ],
  "favorite": false,
  "ingredients": [
    {
      "name": "",
      "ingredients": [
        [
          {
            "name": "butter",
            "minAmount": 100,
            "maxAmount": 100,
            "unit": "g",
            "comment": "cubed",
            "kind": 1,
            "hasGluten": false,
            "hasDairy": true,
            "hasSugar": false,
            "seasons": []
          }
        ],
        [
          {
            "name": "chocolate",
            "modifier": "~50%",
            "minAmount": 200,
            "maxAmount": 200,
            "unit": "g",
            "comment": "broken into pieces",
            "kind": 0,
            "hasGluten": false,
            "hasDairy": false,
            "hasSugar": false,
            "seasons": []
          }
        ],
        [
          {
            "name": "egg",
            "modifier": "medium",
            "minAmount": 4,
            "maxAmount": 4,
            "kind": 1,
            "hasGluten": false,
            "hasDairy": false,
            "hasSugar": false,
            "seasons": []
          }
        ],
        [
          {
            "name": "sugar",
            "modifier": "caster",
            "minAmount": 100,
            "maxAmount": 100,
            "unit": "g",
            "kind": 0,
            "hasGluten": false,
            "hasDairy": false,
            "hasSugar": true,
            "seasons": []
          }
        ],
        [
          {
            "name": "sugar",
            "modifier": "brown",
            "minAmount": 50,
            "maxAmount": 50,
            "unit": "g",
            "kind": 0,
            "hasGluten": false,
            "hasDairy": false,
            "hasSugar": true,
            "seasons": []
          }
        ],
        [
          {
            "name": "all-purpose flour",
            "minAmount": 100,
            "maxAmount": 100,
            "unit": "g",
            "kind": 0,
            "hasGluten": true,
            "hasDairy": false,
            "hasSugar": false,
            "seasons": []
          }
        ],
        [
          {
            "name": "baking powder",
            "minAmount": 5,
            "maxAmount": 5,
            "unit": "g",
            "kind": 0,
            "hasGluten": false,
            "hasDairy": false,
            "hasSugar": false,
            "seasons": []
          }
        ],
        [
          {
            "name": "cocoa powder",
            "modifier": "unsweetened",
            "minAmount": 30,
            "maxAmount": 30,
            "unit": "g",
            "kind": 0,
            "hasGluten": false,
            "hasDairy": false,
            "hasSugar": false,
            "seasons": []
          }
        ],
        [
          {
            "name": "dried cranberry",
            "minAmount": 100,
            "maxAmount": 100,
            "unit": "g",
            "kind": 0,
            "hasGluten": false,
            "hasDairy": false,
            "hasSugar": true,
            "seasons": []
          }
        ]
      ]
    }
  ],
  "keywords": [],
  "notes": [
    "Serve warm or cool, sprinkled with icing sugar. "
  ],
  "overnight": false,
  "slug": "chocolate-brownies-with-dried-cranberries",
  "source": "This recipe is based on Paul Hollywood’s book “How to Bake”.",
  "steps": [
    {
      "name": "",
      "steps": [
        {
          "text": "Heat your oven to 180˚C. Line a 20 cm square baking tin with baking parchment.",
          "pause": false
        },
        {
          "text": "Put the butter and chocolate into a heatproof bowl and melt together over a pan of simmering water. Leave to cool slightly.",
          "pause": false
        },
        {
          "text": "Using an electric hand-held whisk, whisk the eggs and sugar together until the mixture is pale and thick enough to hold a trail when the beaters are lifted.",
          "pause": false
        },
        {
          "text": "Carefully fold the chocolate mixture into the whisked egg mixture. Sift the flour, baking powder and cocoa together over the mixture and gently fold these in too. Finally, fold in the dried cranberries and walnuts. Pour the mixture into the prepared baking tin.",
          "pause": false
        },
        {
          "text": "Bake for 25–30 minutes until nicely crusted but still soft in the middle.",
          "pause": false
        }
      ]
    }
  ],
  "tags": [
    "Baking",
    "Dessert"
  ],
  "time": 60,
  "title": "Chocolate brownies with dried cranberries",
  "tools": [
    "mixer"
  ],
  "yields": {
    "amount": 1,
    "unit": "tray"
  },
  "images": [
    {
      "url": "https://eu-central-1.graphassets.com/Aeh74QOS5TIWHefSmr6nTz/IS73aYruS9CitDm3sCWA",
      "handle": "IS73aYruS9CitDm3sCWA",
      "width": 2637,
      "height": 3782
    }
  ],
  "subrecipes": [],
  "recipes": [],
  "seasons": [],
  "chart": [
    {
      "type": "CookInOven",
      "subtype": "bake",
      "value": "25-30 minutes",
      "covered": false,
      "overnight": false
    }
  ],
  "tips": [],
  "warnings": [],
  "vegan": false,
  "vegetarian": true,
  "glutenFree": false,
  "lowGluten": false,
  "dairyFree": false,
  "noAddedSugar": false
}
