{
  "createdAt": "2022-08-23T11:48:01.190Z",
  "cuisines": [
    "Italian",
    "Klatzlandian"
  ],
  "description": "We don't cook pasta often but almost every time we travel, we cook a variation of this pasta with a lot of vegetables in a hotel or aribnb kitchen. It doesn't require many tools, doesn't leave too many leftover ingredients, could be cooked with whatever vegetables you find in a farmers' market or a supermarket, and with any pasta, you like and could get your hands on. And while cooking in a hotel or airbnb is usually extremely frustrating, it's a great pleasure to eat your own dinner after a full day of exploring a new (or not new, which is equally good) city.",
  "favorite": false,
  "ingredients": [
    {
      "name": "",
      "ingredients": [
        [
          {
            "name": "chile",
            "minAmount": 1,
            "maxAmount": 1,
            "kind": 0,
            "hasGluten": false,
            "hasDairy": false,
            "hasSugar": false,
            "seasons": []
          }
        ],
        [
          {
            "name": "onion",
            "minAmount": 1,
            "maxAmount": 1,
            "kind": 0,
            "hasGluten": false,
            "hasDairy": false,
            "hasSugar": false,
            "seasons": []
          }
        ],
        [
          {
            "name": "garlic",
            "minAmount": 3,
            "maxAmount": 3,
            "unit": "clove",
            "kind": 0,
            "hasGluten": false,
            "hasDairy": false,
            "hasSugar": false,
            "seasons": []
          }
        ],
        [
          {
            "name": "bell pepper",
            "modifier": "red",
            "minAmount": 1,
            "maxAmount": 1,
            "kind": 0,
            "hasGluten": false,
            "hasDairy": false,
            "hasSugar": false,
            "seasons": []
          }
        ],
        [
          {
            "name": "bell pepper",
            "modifier": "green",
            "minAmount": 1,
            "maxAmount": 1,
            "kind": 0,
            "hasGluten": false,
            "hasDairy": false,
            "hasSugar": false,
            "seasons": []
          }
        ],
        [
          {
            "name": "zucchini",
            "minAmount": 0.5,
            "maxAmount": 0.5,
            "kind": 0,
            "hasGluten": false,
            "hasDairy": false,
            "hasSugar": false,
            "seasons": [
              6,
              7,
              8
            ]
          }
        ],
        [
          {
            "name": "tomato",
            "modifier": "cherry",
            "minAmount": 8,
            "maxAmount": 10,
            "kind": 0,
            "hasGluten": false,
            "hasDairy": false,
            "hasSugar": false,
            "seasons": [
              3,
              4,
              5,
              6,
              7,
              8,
              9
            ]
          }
        ],
        [
          {
            "name": "olive",
            "kind": 0,
            "hasGluten": false,
            "hasDairy": false,
            "hasSugar": false,
            "seasons": []
          }
        ],
        [
          {
            "name": "pasta",
            "minAmount": 250,
            "maxAmount": 250,
            "unit": "g",
            "kind": 0,
            "hasGluten": true,
            "hasDairy": false,
            "hasSugar": false,
            "seasons": []
          }
        ],
        [
          {
            "name": "tomato paste",
            "minAmount": 100,
            "maxAmount": 100,
            "unit": "g",
            "kind": 0,
            "hasGluten": false,
            "hasDairy": false,
            "hasSugar": false,
            "seasons": []
          }
        ],
        [
          {
            "name": "black pepper",
            "modifier": "ground",
            "kind": 0,
            "hasGluten": false,
            "hasDairy": false,
            "hasSugar": false,
            "seasons": []
          }
        ],
        [
          {
            "name": "chile flakes",
            "kind": 0,
            "hasGluten": false,
            "hasDairy": false,
            "hasSugar": false,
            "seasons": []
          }
        ],
        [
          {
            "name": "cheese",
            "minAmount": 100,
            "maxAmount": 100,
            "unit": "g",
            "kind": 1,
            "hasGluten": false,
            "hasDairy": true,
            "hasSugar": false,
            "seasons": []
          }
        ],
        [
          {
            "name": "salt",
            "kind": 0,
            "hasGluten": false,
            "hasDairy": false,
            "hasSugar": false,
            "seasons": []
          }
        ],
        [
          {
            "name": "olive oil",
            "kind": 0,
            "hasGluten": false,
            "hasDairy": false,
            "hasSugar": false,
            "seasons": []
          }
        ]
      ]
    }
  ],
  "keywords": [],
  "notes": [
    "We usually take with us a small jar of salt, and small mills with black pepper and chili flakes. Spices in hotels are usually very old, and sometimes there are none at all. ",
    "If there's no cooking oil of any kind, feel free to use butter."
  ],
  "overnight": false,
  "slug": "travelers-pasta",
  "steps": [
    {
      "name": "",
      "steps": [
        {
          "text": "Put a pot of generously salted water to boil.",
          "pause": false
        },
        {
          "text": "Prepare the vegetables. **Onion:** peel, halve, and cut into 1/2 cm slices. **Garlic:** peel and roughly chop. **Chili:** remove the seeds, and cut as thing as possible. **Bell peppers:** remove the seeds, and roughly chop. **Zucchini:** remove the ends, halve lengthwise, and cut into 1/2 half-moons. **Cherry tomatoes:** halve. **Olives:** halve lengthwise.",
          "pause": false
        },
        {
          "text": "In a pan set on medium heat with olive oil or butter, sauté onions, chili, and garlic, until the onions are transparent.",
          "pause": false
        },
        {
          "text": "Add the zucchini to the pan, and cook for a few minutes.",
          "pause": false
        },
        {
          "text": "Add the bell pepper to the pan, and cook until the zucchini has softened but is still a bit crunchy.",
          "pause": false
        },
        {
          "text": "When the water starts to boil, add the pasta, and cook for 1-2 minutes less than recommended on a package.",
          "pause": false
        },
        {
          "text": "Save one cup of pasta water, and discard the rest. Put the pot with the pasta back on the stove, and reduce the heat to medium-low.",
          "pause": false
        },
        {
          "text": "Add the tomato sauce to the pasta (use a bit of pasta water to rinse the jar, and add this to the pasta too).",
          "pause": false
        },
        {
          "text": "Add the cherry tomatoes, the olives, and the vegetables to the pasta, and thoroughly mix everything. Add more salt if needed, and add black pepper and chili flakes. Cook for a few minutes to warm up all the ingredients and finish cooking the pasta.",
          "pause": false
        },
        {
          "text": "Add pieces of cheese to the pasta, mix thoroughly, and serve.",
          "pause": false
        }
      ]
    }
  ],
  "tags": [
    "Lunch",
    "Dinner",
    "Noodles",
    "Travel"
  ],
  "time": 30,
  "title": "Traveler’s pasta",
  "tools": [],
  "yields": {
    "amount": 4,
    "unit": "portion"
  },
  "images": [
    {
      "url": "https://eu-central-1.graphassets.com/Aeh74QOS5TIWHefSmr6nTz/8jwRushSRAi3oO1YYNlw",
      "handle": "8jwRushSRAi3oO1YYNlw",
      "width": 5828,
      "height": 4082
    }
  ],
  "subrecipes": [],
  "recipes": [],
  "seasons": [
    6,
    7,
    8
  ],
  "chart": [],
  "tips": [
    "The easiest way to peel garlic is to smash it: put a clove of garlic on a cutting board, put your chef’s knife on top of it so the blade side lays on the clove, and hit the side of the knife with your hand. Now you could peel the clove."
  ],
  "warnings": [],
  "vegan": false,
  "vegetarian": true,
  "glutenFree": false,
  "lowGluten": false,
  "dairyFree": false,
  "noAddedSugar": true
}
